CHANGES.txt
MANIFEST.in
README.md
setup.py
praekelt_pyramid_celery.egg-info/PKG-INFO
praekelt_pyramid_celery.egg-info/SOURCES.txt
praekelt_pyramid_celery.egg-info/dependency_links.txt
praekelt_pyramid_celery.egg-info/entry_points.txt
praekelt_pyramid_celery.egg-info/not-zip-safe
praekelt_pyramid_celery.egg-info/requires.txt
praekelt_pyramid_celery.egg-info/top_level.txt
pyramid_celery/__init__.py
pyramid_celery/commands/__init__.py
pyramid_celery/commands/celery.py
pyramid_celery/commands/celerybeat.py
pyramid_celery/commands/celeryctl.py
pyramid_celery/commands/celeryd.py
pyramid_celery/commands/celeryev.py
pyramid_celery/tests/__init__.py
pyramid_celery/tests/test_celery.py