Metadata-Version: 1.1
Name: praekelt-pyramid-celery
Version: 1.4.0
Summary: Celery integration with pyramid
Home-page: https://github.com/sontek/pyramid_celery
Author: John Anderson
Author-email: sontek@gmail.com
License: BSD
Keywords: paste pyramid celery message queue amqp job task distributed
Platform: UNKNOWN
Classifier: Development Status :: 4 - Beta
Classifier: Environment :: Web Environment
Classifier: Intended Audience :: Developers
Classifier: License :: OSI Approved :: BSD License
Classifier: Operating System :: OS Independent
Classifier: Programming Language :: Python
Classifier: Topic :: Internet :: WWW/HTTP :: Dynamic Content
Classifier: Topic :: Software Development :: Libraries :: Python Modules
